MANIFEST.in
Pipfile
README.md
requirements.txt
setup.py
structor/__init__.py
structor/builder.py
structor/check_status.py
structor/custom_cookie_jar.py
structor/custom_request.py
structor/downloadermiddlewares.py
structor/item_collector.py
structor/pipelines.py
structor/scheduler.py
structor/settings.py
structor/spider_feeder.py
structor/stats_collectors.py
structor/user_agents.list
structor/utils.py
structor/items/__init__.py
structor/items/baidump3_item.py
structor/items/douban_item.py
structor/spiders/__init__.py
structor/spiders/baidump3_spider.py
structor/spiders/douban_spider.py
structor/templates/project/scrapy.cfg
structor/templates/project/${project_name}/settings.py.tmpl
structor/templates/project/${project_name}/items/__init__.py
structor/templates/project/${project_name}/items/baidump3_item.py
structor/templates/project/${project_name}/items/douban_item.py
structor/templates/project/${project_name}/spiders/__init__.py
structor/templates/project/${project_name}/spiders/baidump3_spider.py
structor/templates/project/${project_name}/spiders/douban_spider.py
structor/templates/spider/item.py.tmpl
structor/templates/spider/spider.py.tmpl
structure_spider.egg-info/PKG-INFO
structure_spider.egg-info/SOURCES.txt
structure_spider.egg-info/dependency_links.txt
structure_spider.egg-info/entry_points.txt
structure_spider.egg-info/requires.txt
structure_spider.egg-info/top_level.txt
structure_spider.egg-info/zip-safe