Metadata-Version: 2.1
Name: structure-spider
Version: 1.3.1
Summary: multi requests to combine a structure item.
Home-page: https://www.github.com/ShichaoMa/structure_spider
Author: cn
Author-email: cnaafhvk@foxmail.com
License: MIT
Keywords: spider
Platform: UNKNOWN
Classifier: License :: OSI Approved :: MIT License
Classifier: Programming Language :: Python :: 3
Classifier: Intended Audience :: Developers
Classifier: Operating System :: Unix
